agentwebsearch/__init__.py
agentwebsearch/logger.py
agentwebsearch/py.typed
agentwebsearch/embedding/__init__.py
agentwebsearch/embedding/base.py
agentwebsearch/embedding/openai.py
agentwebsearch/embedding/utils.py
agentwebsearch/indexsearch/__init__.py
agentwebsearch/indexsearch/base.py
agentwebsearch/indexsearch/hnsw.py
agentwebsearch/llm/__init__.py
agentwebsearch/llm/base.py
agentwebsearch/llm/openai.py
agentwebsearch/mcp/__init__.py
agentwebsearch/mcp/example.py
agentwebsearch/mcp/server.py
agentwebsearch/rest/__init__.py
agentwebsearch/rest/example.py
agentwebsearch/rest/server.py
agentwebsearch/search/client/__init__.py
agentwebsearch/search/client/base.py
agentwebsearch/search/client/default.py
agentwebsearch/search/client/searchapi.py
agentwebsearch/search/client/serpapi.py
agentwebsearch/utils/.gitkeep
agentwebsearch/webscraper/__init__.py
agentwebsearch/webscraper/base.py
agentwebsearch/webscraper/default.py
agentwebsearch/webscraper/utils.py
agentwebsearch/websearch/dto.py
agentwebsearch/websearch/request.py
agentwebsearch/websearch/response.py
agentwebsearch/websearch/websearch.py
agentwebsearch/websearch/prompts/__init__.py
agentwebsearch/websearch/prompts/prompts.py
agentwebsearch/websearch/prompts/markdown/google_vector_search.md
agentwebsearch/websearch/prompts/markdown/summarize_websearch_result.md
agentwebsearch_py-0.2.0.dist-info/METADATA
agentwebsearch_py-0.2.0.dist-info/WHEEL
agentwebsearch_py-0.2.0.dist-info/RECORD
