Metadata-Version: 2.4
Name: agentwebsearch-py
Version: 0.2.0
Summary: Python package for semantic relevant web search results.
Author-email: Enrico Goerlitz <rico.goerlitz@gmail.com>
Requires-Python: >=3.13
Requires-Dist: fastapi>=0.116.1
Requires-Dist: fastmcp>=2.10.6
Requires-Dist: googlesearch-python>=1.3.0
Requires-Dist: hnswlib>=0.8.0
Requires-Dist: numpy>=2.3.1
Requires-Dist: openai>=1.97.0
Requires-Dist: pdfplumber>=0.11.7
Requires-Dist: pydantic>=2.11.7
Requires-Dist: pytest>=8.4.1
Requires-Dist: tiktoken>=0.9.0
